pytest_tally/__init__.py
pytest_tally/classes.py
pytest_tally/dashboard.py
pytest_tally/plugin.py
pytest_tally/pytest_reportlog.py
pytest_tally/utils.py
pytest_tally/clients/app.py
pytest_tally/clients/rich_dashboard.py
pytest_tally/clients/tk_client.py
pytest_tally/clients/templates/index.html
pytest_tally-1.3.1.dist-info/LICENSE
pytest_tally-1.3.1.dist-info/METADATA
pytest_tally-1.3.1.dist-info/WHEEL
pytest_tally-1.3.1.dist-info/entry_points.txt
pytest_tally-1.3.1.dist-info/top_level.txt
pytest_tally-1.3.1.dist-info/RECORD
