Metadata-Version: 2.1
Name: pytest-tally
Version: 1.3.1
Summary: A Pytest plugin to generate realtime summary stats, and display them in-console using a text-based dashboard.
Home-page: https://github.com/jeffwright13/pytest-tally
Author: Jeff Wright
Author-email: jeff.washcloth@gmail.com
License: MIT
Keywords: pytest pytest-plugin testing tui rich blessed
Classifier: Framework :: Pytest
Classifier: Development Status :: 4 - Beta
Classifier: Intended Audience :: Developers
Classifier: Topic :: Software Development :: Testing
Classifier: Programming Language :: Python :: 3.8
Classifier: Programming Language :: Python :: 3.9
Classifier: Programming Language :: Python :: 3.10
Classifier: Programming Language :: Python :: 3.11
Classifier: Operating System :: OS Independent
Classifier: License :: OSI Approved :: MIT License
Requires-Python: >=3.8
License-File: LICENSE
Requires-Dist: blessed (==1.20.0)
Requires-Dist: count-timer (==0.3.8)
Requires-Dist: flask (==2.3.2)
Requires-Dist: pytest (>=6.2.5)
Requires-Dist: quantiphy (==2.19)
Requires-Dist: rich (==13.3.2)
Requires-Dist: single-source (==0.3.0)
Requires-Dist: strip-ansi (==0.1.1)
Requires-Dist: watchdog (==3.0.0)
